cilogon_tokenauth/__init__.py
cilogon_tokenauth/admin.py
cilogon_tokenauth/apps.py
cilogon_tokenauth/auth.py
cilogon_tokenauth/client.py
cilogon_tokenauth/exc.py
cilogon_tokenauth/models.py
cilogon_tokenauth/migrations/0001_initial.py
cilogon_tokenauth/migrations/__init__.py
cilogon_tokenauth-0.4.0.dist-info/METADATA
cilogon_tokenauth-0.4.0.dist-info/WHEEL
cilogon_tokenauth-0.4.0.dist-info/top_level.txt
cilogon_tokenauth-0.4.0.dist-info/RECORD
